{
  "child_summary": {
    "Surface Features": 2,
    "Bathymetric Data Products": 4,
    "Physical Processes": 3,
    "Safety And Mitigation": 2,
    "Objectives": 3,
    "Route And Trajectory": 7,
    "Hazards": 1,
    "Survey Data": 2,
    "Performance": 1,
    "uncategorised": 4,
    "Seafloor Characterization": 1,
    "Hardware": 4
  },
  "parent_summary": {
    "Terrain And Bathymetry": 7,
    "Navigation And Positioning": 8,
    "Environmental And Oceanographic Conditions": 2,
    "Threats And Risk Management": 3,
    "Mission Parameters And Objectives": 3,
    "Data Products And Requirements": 2,
    "Vehicle Capabilities And Constraints": 5,
    "uncategorised": 4
  }
}